pyxltab/__init__.py
pyxltab/classes.py
pyxltab/pyxltab.py
pyxltab-0.2.1.dist-info/LICENSE
pyxltab-0.2.1.dist-info/METADATA
pyxltab-0.2.1.dist-info/WHEEL
pyxltab-0.2.1.dist-info/top_level.txt
pyxltab-0.2.1.dist-info/RECORD
