Metadata-Version: 2.1
Name: pyxltab
Version: 0.2.1
Summary: Extends openpyxl for easier operation on Excel tables.
Home-page: https://github.com/blakeNaccarato/pyxltab
Author: Blake Naccarato
License: UNKNOWN
Platform: UNKNOWN
Requires-Python: >=3.7
Requires-Dist: openpyxl (>=3.0.5)
